token_shap/__init__.py
token_shap/baseline.py
token_shap/prompt_engineering.py
token_shap/token_shap.py
TokenSHAP-0.2.2.dist-info/LICENSE
TokenSHAP-0.2.2.dist-info/METADATA
TokenSHAP-0.2.2.dist-info/WHEEL
TokenSHAP-0.2.2.dist-info/top_level.txt
TokenSHAP-0.2.2.dist-info/RECORD
