Metadata-Version: 2.1
Name: TokenSHAP
Version: 0.2.2
Summary: Paper Implementation: "TokenSHAP: Interpreting Large Language Models with Monte Carlo Shapley Value Estimation"
Home-page: https://github.com/ronigold/TokenSHAP
Author: Roni Goldshmidt
Author-email: roni.goldshmidt@getnexar.com
Project-URL: Bug Reports, https://github.com/ronigold/TokenSHAP/issues
Project-URL: Source, https://github.com/ronigold/TokenSHAP
Keywords: shapley values interpretation NLP AI
Classifier: Development Status :: 3 - Alpha
Classifier: Intended Audience :: Developers
Classifier: License :: OSI Approved :: MIT License
Classifier: Programming Language :: Python :: 3
Classifier: Programming Language :: Python :: 3.7
Classifier: Programming Language :: Python :: 3.8
Classifier: Programming Language :: Python :: 3.9
Classifier: Operating System :: OS Independent
Requires-Python: >=3.6
License-File: LICENSE
Requires-Dist: numpy >=1.19
Requires-Dist: pandas >=1.1
Requires-Dist: matplotlib >=3.3
Requires-Dist: scikit-learn >=0.23
Requires-Dist: transformers >=4.0
Requires-Dist: tqdm >=4.50
Requires-Dist: PyYAML >=5.3
Requires-Dist: requests >=2.24
